synpivimage/__init__.py
synpivimage/_version.py
synpivimage/camera.py
synpivimage/codemeta.py
synpivimage/component.py
synpivimage/core.py
synpivimage/io.py
synpivimage/laser.py
synpivimage/noise.py
synpivimage/particles.py
synpivimage/utils.py
synpivimage/validation.py
synpivimage/gui/__init__.py
synpivimage/gui/core.py
synpivimage/gui/plotting.py
synpivimage/gui/lib/__init__.py
synpivimage/gui/lib/corr.py
synpivimage/gui/lib/plotting.py
synpivimage-1.0.0a9.dist-info/licenses/LICENSE
synpivimage-1.0.0a9.dist-info/METADATA
synpivimage-1.0.0a9.dist-info/WHEEL
synpivimage-1.0.0a9.dist-info/top_level.txt
synpivimage-1.0.0a9.dist-info/RECORD
