Metadata-Version: 2.4
Name: synpivimage
Version: 1.0.0a9
Summary: Tool to build synthetic Particle Image Velocimetry (PIV) images
Author-email: Matthias Probst <matth.probst@gmail.com>
License: MIT
Project-URL: Homepage, https://github.com/MatthiasProbst/synpivimage
Project-URL: Repository, https://github.com/MatthiasProbst/synpivimage
Project-URL: Issues, https://github.com/MatthiasProbst/synpivimage/issues
Keywords: piv,particle image velocimetry,synthetic images,scientific computing
Classifier: Programming Language :: Python :: 3
Classifier: License :: OSI Approved :: MIT License
Classifier: Programming Language :: Python :: 3.9
Classifier: Programming Language :: Python :: 3.10
Classifier: Programming Language :: Python :: 3.11
Classifier: Programming Language :: Python :: 3.12
Classifier: Operating System :: OS Independent
Classifier: Development Status :: 3 - Alpha
Requires-Python: <3.13,>=3.9
License-File: LICENSE
Requires-Dist: numpy
Requires-Dist: pandas
Requires-Dist: pathlib
Requires-Dist: pyyaml>=6.0.0
Requires-Dist: tqdm
Requires-Dist: matplotlib
Requires-Dist: python-dotenv
Requires-Dist: opencv-python
Requires-Dist: scipy
Requires-Dist: pydantic
Requires-Dist: ontolutils<0.28.0,>=0.27.0
Requires-Dist: ssnolib==2.2.0.3
Requires-Dist: pivmetalib<3.1.1.0,>=3.1.0.1
Requires-Dist: pivimage
Requires-Dist: pint
Provides-Extra: test
Requires-Dist: h5py; extra == "test"
Requires-Dist: pytest>=7.1.2; extra == "test"
Requires-Dist: pytest-cov; extra == "test"
Provides-Extra: gui
Requires-Dist: PyQt5; extra == "gui"
Requires-Dist: xarray; extra == "gui"
Provides-Extra: doc
Requires-Dist: sphinx>=4.5.0; extra == "doc"
Requires-Dist: sphinx_book_theme; extra == "doc"
Requires-Dist: sphinx-copybutton; extra == "doc"
Requires-Dist: scikit-image; extra == "doc"
Requires-Dist: scikit-learn; extra == "doc"
Requires-Dist: sphinx-design; extra == "doc"
Requires-Dist: myst-nb; extra == "doc"
Requires-Dist: nbsphinx; extra == "doc"
Requires-Dist: sphinxcontrib-bibtex; extra == "doc"
Requires-Dist: sphinx-math-dollar; extra == "doc"
Requires-Dist: h5rdmtoolbox<2.6.0,>=2.5.4; extra == "doc"
Requires-Dist: xmltodict; extra == "doc"
Provides-Extra: dev
Requires-Dist: synpivimage[doc,test]; extra == "dev"
Requires-Dist: pylint; extra == "dev"
Provides-Extra: complete
Requires-Dist: synpivimage[doc,gui,test]; extra == "complete"
Dynamic: license-file
